{
    "height": 1080,
    "width": 1920,
    "crs": "PROJCRS[\"WGS 84 / UTM zone 43N\",BASEGEOGCRS[\"WGS 84\",ENSEMBLE[\"World Geodetic System 1984 ensemble\",MEMBER[\"World Geodetic System 1984 (Transit)\"],MEMBER[\"World Geodetic System 1984 (G730)\"],MEMBER[\"World Geodetic System 1984 (G873)\"],MEMBER[\"World Geodetic System 1984 (G1150)\"],MEMBER[\"World Geodetic System 1984 (G1674)\"],MEMBER[\"World Geodetic System 1984 (G1762)\"],MEMBER[\"World Geodetic System 1984 (G2139)\"],MEMBER[\"World Geodetic System 1984 (G2296)\"],ELLIPSOID[\"WGS 84\",6378137,298.257223563,LENGTHUNIT[\"metre\",1]],ENSEMBLEACCURACY[2.0]],PRIMEM[\"Greenwich\",0,ANGLEUNIT[\"degree\",0.0174532925199433]],ID[\"EPSG\",4326]],CONVERSION[\"UTM zone 43N\",METHOD[\"Transverse Mercator\",ID[\"EPSG\",9807]],PARAMETER[\"Latitude of natural origin\",0,ANGLEUNIT[\"degree\",0.0174532925199433],ID[\"EPSG\",8801]],PARAMETER[\"Longitude of natural origin\",75,ANGLEUNIT[\"degree\",0.0174532925199433],ID[\"EPSG\",8802]],PARAMETER[\"Scale factor at natural origin\",0.9996,SCALEUNIT[\"unity\",1],ID[\"EPSG\",8805]],PARAMETER[\"False easting\",500000,LENGTHUNIT[\"metre\",1],ID[\"EPSG\",8806]],PARAMETER[\"False northing\",0,LENGTHUNIT[\"metre\",1],ID[\"EPSG\",8807]]],CS[Cartesian,2],AXIS[\"(E)\",east,ORDER[1],LENGTHUNIT[\"metre\",1]],AXIS[\"(N)\",north,ORDER[2],LENGTHUNIT[\"metre\",1]],USAGE[SCOPE[\"Navigation and medium accuracy spatial referencing.\"],AREA[\"Between 72\u00b0E and 78\u00b0E, northern hemisphere between equator and 84\u00b0N, onshore and offshore. China. India. Kazakhstan. Kyrgyzstan. Maldives. Pakistan. Russian Federation. Tajikistan.\"],BBOX[0,72,84,78]],ID[\"EPSG\",32643]]",
    "resolution": 0.01,
    "lens_position": null,
    "gcps": {
        "src": [
            [
                1750,
                600
            ],
            [
                1400,
                360
            ],
            [
                420,
                370
            ],
            [
                250,
                470
            ]
        ],
        "dst": [
            [
                366400.72,
                2053619.745
            ],
            [
                366415.789,
                2053631.48
            ],
            [
                366362.501,
                2053663.004
            ],
            [
                366349.972,
                2053652.418
            ]
        ],
        "h_ref": 0.0,
        "z_0": 0
    },
    "window_size": 25,
    "is_nadir": false,
    "rvec": null,
    "tvec": null,
    "camera_matrix": [
        [
            3839.328857421875,
            0.0,
            960.0
        ],
        [
            0.0,
            3839.328857421875,
            540.0
        ],
        [
            0.0,
            0.0,
            1.0
        ]
    ],
    "dist_coeffs": [
        [
            0.0
        ],
        [
            0.0
        ],
        [
            0.0
        ],
        [
            0.0
        ],
        [
            0.0
        ]
    ],
    "bbox": "POLYGON ((366207.649119021 2053698.8486921508, 366416.9415022732 2053660.0953592279, 366409.68606268195 2053620.9114199623, 366200.3936794299 2053659.6647528855, 366207.649119021 2053698.8486921508))"
}